nutritionix/__init__.py
nutritionix/nutritionix.py
nutritionix_unofficial-1.0.0.dist-info/METADATA
nutritionix_unofficial-1.0.0.dist-info/WHEEL
nutritionix_unofficial-1.0.0.dist-info/top_level.txt
nutritionix_unofficial-1.0.0.dist-info/RECORD
